tidyspotify.py
tidyspotify-0.0.1.dist-info/DESCRIPTION.rst
tidyspotify-0.0.1.dist-info/METADATA
tidyspotify-0.0.1.dist-info/RECORD
tidyspotify-0.0.1.dist-info/WHEEL
tidyspotify-0.0.1.dist-info/metadata.json
tidyspotify-0.0.1.dist-info/top_level.txt
